groclake_deployer/__init__.py
groclake_deployer/deploy.py
groclake_deployer-0.1.1.dist-info/METADATA
groclake_deployer-0.1.1.dist-info/WHEEL
groclake_deployer-0.1.1.dist-info/entry_points.txt
groclake_deployer-0.1.1.dist-info/top_level.txt
groclake_deployer-0.1.1.dist-info/RECORD
