Metadata-Version: 2.1
Name: groclake-deployer
Version: 0.1.1
Summary: Installs Docker and runs groclake container
Home-page: UNKNOWN
License: UNKNOWN
Platform: UNKNOWN
Requires-Python: >=3.6
